aiosmshub/__init__.py
aiosmshub/__version__.py
aiosmshub/models/__init__.py
aiosmshub-0.0.1.dist-info/METADATA
aiosmshub-0.0.1.dist-info/WHEEL
aiosmshub-0.0.1.dist-info/top_level.txt
aiosmshub-0.0.1.dist-info/RECORD
